.gitignore
MANIFEST.in
README.txt
bootstrap.py
buildout.cfg
setup.py
test-plone-4.3.x.cfg
cs/__init__.py
cs.auth.twitter.egg-info/PKG-INFO
cs.auth.twitter.egg-info/SOURCES.txt
cs.auth.twitter.egg-info/dependency_links.txt
cs.auth.twitter.egg-info/entry_points.txt
cs.auth.twitter.egg-info/namespace_packages.txt
cs.auth.twitter.egg-info/not-zip-safe
cs.auth.twitter.egg-info/requires.txt
cs.auth.twitter.egg-info/top_level.txt
cs/auth/__init__.py
cs/auth/twitter/__init__.py
cs/auth/twitter/addform.pt
cs/auth/twitter/config.py
cs/auth/twitter/configure.zcml
cs/auth/twitter/controlpanel.py
cs/auth/twitter/interfaces.py
cs/auth/twitter/login.py
cs/auth/twitter/plugin.py
cs/auth/twitter/rebuild_i18n.sh
cs/auth/twitter/setuphandlers.py
cs/auth/twitter/tests.py
cs/auth/twitter/user.py
cs/auth/twitter/locales/cs.auth.twitter-manual.pot
cs/auth/twitter/locales/cs.auth.twitter.pot
cs/auth/twitter/locales/es/LC_MESSAGES/cs.auth.twitter.po
cs/auth/twitter/locales/eu/LC_MESSAGES/cs.auth.twitter.po
cs/auth/twitter/profiles/default/actions.xml
cs/auth/twitter/profiles/default/browserlayer.xml
cs/auth/twitter/profiles/default/controlpanel.xml
cs/auth/twitter/profiles/default/cs.auth.twitter-various.txt
cs/auth/twitter/profiles/default/metadata.xml
cs/auth/twitter/profiles/default/registry.xml
docs/HISTORY.txt
docs/INSTALL.txt
docs/LICENSE.GPL
docs/LICENSE.txt