Metadata-Version: 1.1
Name: cs.auth.twitter
Version: 1.1.1
Summary: Twitter based login for Plone
Home-page: https://github.com/codesyntax/cs.auth.twitter/
Author: Mikel Larreategi
Author-email: mlarreategi@codesyntax.com
License: GPL
Keywords: pas plugin plone authentication twitter
Platform: UNKNOWN
Classifier: Framework :: Plone
Classifier: Programming Language :: Python
